{"frames": {

"obstacleboxes.png":
{
	"frame": {"x":0,"y":0,"w":192,"h":32},
	"rotated": false,
	"trimmed": false,
	"spriteSourceSize": {"x":0,"y":0,"w":192,"h":32},
	"sourceSize": {"w":192,"h":32}
}},
"meta": {
	"app": "https://www.codeandweb.com/texturepacker",
	"version": "1.0",
	"image": "obstacleboxes.png",
	"format": "RGBA8888",
	"size": {"w":192,"h":32},
	"scale": "1",
	"smartupdate": "$TexturePacker:SmartUpdate:2fc5043db3c1304567d9c1cc10691d65:eee2f81be37f95219ec2708cd7a121ff:bbd40c130d076315f5bb132327e381bc$"
}
}
